topquant_ksk/__init__.py
topquant_ksk/load_data.py
topquant_ksk/plot.py
topquant_ksk/risk_return_metrics.py
topquant_ksk/tools.py
topquant_ksk-0.1.6.dist-info/METADATA
topquant_ksk-0.1.6.dist-info/WHEEL
topquant_ksk-0.1.6.dist-info/top_level.txt
topquant_ksk-0.1.6.dist-info/RECORD
